<?xml version="1.0" encoding="utf-8" ?>
<dwsync>
<file name="LICENSE.txt" server="www.ctba.co.za/public_html/" local="130439518755755595" remote="130439481000000000" Dst="0" />
<file name="README.txt" server="www.ctba.co.za/public_html/" local="130439518755875577" remote="130439481000000000" Dst="0" />
<file name="notifications.admin.inc" server="www.ctba.co.za/public_html/" local="130439518762376925" remote="130439481000000000" Dst="0" />
<file name="notifications.event.inc" server="www.ctba.co.za/public_html/" local="130439518762736866" remote="130439481000000000" Dst="0" />
<file name="notifications.field.inc" server="www.ctba.co.za/public_html/" local="130439518763476915" remote="130439481000000000" Dst="0" />
<file name="notifications.info" server="www.ctba.co.za/public_html/" local="130439518766537495" remote="130439481000000000" Dst="0" />
<file name="notifications.install" server="www.ctba.co.za/public_html/" local="130439518766867503" remote="130439481000000000" Dst="0" />
<file name="notifications.list.inc" server="www.ctba.co.za/public_html/" local="130439518769522109" remote="130439481000000000" Dst="0" />
<file name="notifications.manage.inc" server="www.ctba.co.za/public_html/" local="130439518769852100" remote="130439481000000000" Dst="0" />
<file name="notifications.message.inc" server="www.ctba.co.za/public_html/" local="130439518770022104" remote="130439481000000000" Dst="0" />
<file name="notifications.object.inc" server="www.ctba.co.za/public_html/" local="130439518773616464" remote="130439481000000000" Dst="0" />
<file name="notifications.module" server="www.ctba.co.za/public_html/" local="130439518774306463" remote="130439481000000000" Dst="0" />
<file name="notifications.pages.inc" server="www.ctba.co.za/public_html/" local="130439518775386390" remote="130439481000000000" Dst="0" />
<file name="notifications.subscription.inc" server="www.ctba.co.za/public_html/" local="130439518777963343" remote="130439481000000000" Dst="0" />
<file name="notifications.template.inc" server="www.ctba.co.za/public_html/" local="130439518779298437" remote="130439481000000000" Dst="0" />
</dwsync>